pyservices/__init__.py
pyservices/meta_service.py
pyservices/signals.py
pyservices-0.0.1.1.dist-info/LICENSE
pyservices-0.0.1.1.dist-info/METADATA
pyservices-0.0.1.1.dist-info/WHEEL
pyservices-0.0.1.1.dist-info/top_level.txt
pyservices-0.0.1.1.dist-info/RECORD
